{"posts": {"count": "3836596", "offset": "192", "post": [{"height": "1600", "score": "", "file_url": "https://safebooru.org/images/3845/12c760e519c7fda2d5a1ccf55878d2963ff957fc.png", "parent_id": "", "sample_url": "https://safebooru.org/samples/3845/sample_12c760e519c7fda2d5a1ccf55878d2963ff957fc.jpg", "sample_width": "850", "sample_height": "1133", "preview_url": "https://safebooru.org/thumbnails/3845/thumbnail_12c760e519c7fda2d5a1ccf55878d2963ff957fc.jpg", "rating": "s", "tags": " 1girl armpits arms_behind_head arms_up ass bangs bare_legs bikini bikini_top_only blonde_hair blue_eyes breasts covered_nipples denim denim_shorts eyebrows_visible_through_hair feet_out_of_frame highres idolmaster idolmaster_cinderella_girls knees_together_feet_apart large_breasts long_hair looking_at_viewer lying multicolored_bikini multicolored_clothes naboo_(naboo03) navel ohtsuki_yui on_side open_mouth short_shorts shorts solo strap_gap swept_bangs swimsuit towel under_boob ", "id": "4016662", "width": "1200", "change": "1652992248", "md5": "a04139ab43693cca41dac9404457c585", "creator_id": "168", "has_children": "false", "created_at": "Thu May 19 20:30:48 +0000 2022", "status": "active", "source": "https://i.pximg.net/img-original/img/2022/05/19/22/00/02/98457858_p0.png", "has_notes": "false", "has_comments": "false", "preview_width": "112", "preview_height": "150"}, {"height": "2552", "score": "0", "file_url": "https://safebooru.org/images/3845/7d921b93f27e7c3d18bd2815ae8a6a0bf3536963.jpg", "parent_id": "", "sample_url": "https://safebooru.org/samples/3845/sample_7d921b93f27e7c3d18bd2815ae8a6a0bf3536963.jpg", "sample_width": "850", "sample_height": "1312", "preview_url": "https://safebooru.org/thumbnails/3845/thumbnail_7d921b93f27e7c3d18bd2815ae8a6a0bf3536963.jpg", "rating": "s", "tags": " 1girl absurdres animal_ears arm_sling bandage_over_one_eye bandaged_head bandages bandaid bandaid_on_face black_hair cat_ears cat_girl cat_tail frown gauze glaring highres hospital_gown intravenous_drip iv_stand messy_hair original satou_(3366_s) sketch sleeves_past_fingers sleeves_past_wrists tail ", "id": "4016661", "width": "1653", "change": "1652992248", "md5": "bcf01ad48ccf01f435360b622d70d953", "creator_id": "168", "has_children": "false", "created_at": "Thu May 19 20:30:47 +0000 2022", "status": "active", "source": "https://twitter.com/kakusatou_3333/status/1487756552056741892", "has_notes": "false", "has_comments": "false", "preview_width": "97", "preview_height": "150"}, {"height": "1985", "score": "0", "file_url": "https://safebooru.org/images/3845/c2ae10d688cc6c7b0e6aa8922bfcfb8b21f822ad.jpg", "parent_id": "", "sample_url": "https://safebooru.org/samples/3845/sample_c2ae10d688cc6c7b0e6aa8922bfcfb8b21f822ad.jpg", "sample_width": "850", "sample_height": "1243", "preview_url": "https://safebooru.org/thumbnails/3845/thumbnail_c2ae10d688cc6c7b0e6aa8922bfcfb8b21f822ad.jpg", "rating": "s", "tags": " clenched_hand clenched_hands crossover drill ebi_frion_(natsuiro_matsuri) fusion g_gundam gaogaigar glowing god_gundam green_eyes gundam highres hololive mecha mechanization no_humans pinguinkotak red_eyes robot sketch solo super_robot v-fin wings yuusha_ou_gaogaigar yuusha_series ", "id": "4016660", "width": "1357", "change": "1652992246", "md5": "b88c868531f952337fdea127fba6d151", "creator_id": "168", "has_children": "false", "created_at": "Thu May 19 20:30:46 +0000 2022", "status": "active", "source": "https://twitter.com/PinguinKotak/status/1525438955373891586", "has_notes": "false", "has_comments": "false", "preview_width": "102", "preview_height": "150"}, {"height": "4093", "score": "", "file_url": "https://safebooru.org/images/3845/d2bb10a284a80ea45adea66029a3208aa3d1a4e4.jpg", "parent_id": "", "sample_url": "https://safebooru.org/samples/3845/sample_d2bb10a284a80ea45adea66029a3208aa3d1a4e4.jpg", "sample_width": "850", "sample_height": "1202", "preview_url": "https://safebooru.org/thumbnails/3845/thumbnail_d2bb10a284a80ea45adea66029a3208aa3d1a4e4.jpg", "rating": "s", "tags": " 1girl absurdres bangs black_sleeves black_wings blue_archive blush eyebrows_visible_through_hair gradient gradient_background halo hat highres koharu_(blue_archive) long_sleeves looking_at_viewer low_wings neckerchief pink_background pink_eyes pink_hair pink_neckerchief rotroto school_uniform serafuku sitting solo thighs twintails wariza white_background wings ", "id": "4016659", "width": "2894", "change": "1652992246", "md5": "987c96fcb24894699f743c74dbb5acd3", "creator_id": "168", "has_children": "false", "created_at": "Thu May 19 20:30:44 +0000 2022", "status": "active", "source": "https://i.pximg.net/img-original/img/2022/05/08/20/05/58/98206765_p0.jpg", "has_notes": "false", "has_comments": "false", "preview_width": "106", "preview_height": "150"}, {"height": "1465", "score": "0", "file_url": "https://safebooru.org/images/3845/238c2d196e0d29bf0b817b41088ef723935f39c7.jpg", "parent_id": "", "sample_url": "https://safebooru.org/images/3845/238c2d196e0d29bf0b817b41088ef723935f39c7.jpg", "sample_width": "805", "sample_height": "1465", "preview_url": "https://safebooru.org/thumbnails/3845/thumbnail_238c2d196e0d29bf0b817b41088ef723935f39c7.jpg", "rating": "s", "tags": " 1girl bangs black_gloves black_legwear blonde_hair blue_eyes breasts china_dress chinese_clothes covered_navel double_bun dress elbow_gloves eyebrows_visible_through_hair feet_out_of_frame girls_frontline gloves hair_ornament hairclip highres long_hair looking_at_viewer medium_breasts no_panties official_alternate_costume qiye_jiexian red_dress sitting smile solo teeth_hold thigh-highs tkb-408_(dance_of_cinnabar)_(girls'_frontline) tkb-408_(girls'_frontline) white_background ", "id": "4016658", "width": "805", "change": "1652992244", "md5": "42f88889f3308c34de5e8dc008924aba", "creator_id": "168", "has_children": "false", "created_at": "Thu May 19 20:30:43 +0000 2022", "status": "active", "source": "https://i.pximg.net/img-original/img/2022/04/13/01/31/35/97591034_p0.jpg", "has_notes": "false", "has_comments": "false", "preview_width": "82", "preview_height": "150"}, {"height": "1331", "score": "0", "file_url": "https://safebooru.org/images/3845/643bf6bee760091886b7efc609f1fc59e06f9473.jpg", "parent_id": "", "sample_url": "https://safebooru.org/images/3845/643bf6bee760091886b7efc609f1fc59e06f9473.jpg", "sample_width": "912", "sample_height": "1331", "preview_url": "https://safebooru.org/thumbnails/3845/thumbnail_643bf6bee760091886b7efc609f1fc59e06f9473.jpg", "rating": "s", "tags": " 1girl animal_ears arm_sling bandage_over_one_eye bandaged_head bandaged_tail bandages black_hair cat_ears cat_girl cat_tail frown highres hospital_gown original satou_(3366_s) short_hair sketch sleeves_past_fingers sleeves_past_wrists tail ", "id": "4016657", "width": "912", "change": "1652992243", "md5": "4179b23ac328f730f3647ef75d8ca596", "creator_id": "168", "has_children": "false", "created_at": "Thu May 19 20:30:43 +0000 2022", "status": "active", "source": "https://twitter.com/kakusatou_3333/status/1488270875162030083", "has_notes": "false", "has_comments": "false", "preview_width": "102", "preview_height": "150"}, {"height": "1179", "score": "0", "file_url": "https://safebooru.org/images/3845/b5da82c16439e30aa01f1868bddcc3ada16d66a1.png", "parent_id": "", "sample_url": "https://safebooru.org/images/3845/b5da82c16439e30aa01f1868bddcc3ada16d66a1.png", "sample_width": "1000", "sample_height": "1179", "preview_url": "https://safebooru.org/thumbnails/3845/thumbnail_b5da82c16439e30aa01f1868bddcc3ada16d66a1.jpg", "rating": "s", "tags": " 2girls apron aqua_eyes beatrice_(re:zero) blonde_hair blue_eyes blush bow crown drill_hair hair_ornament hair_ribbon holding_hands long_hair maid maid_apron maid_day multiple_girls orange_hair petra_leyte re:zero_kara_hajimeru_isekai_seikatsu ribbon s_(hdru2332) short_hair sidelocks symbol-shaped_pupils thumbs_up twin_drills ", "id": "4016656", "width": "1000", "change": "1652992242", "md5": "88fb0c23247eacff0bd3a5aed84b444f", "creator_id": "168", "has_children": "false", "created_at": "Thu May 19 20:30:42 +0000 2022", "status": "active", "source": "https://i.pximg.net/img-original/img/2022/05/19/21/02/55/98456454_p0.png", "has_notes": "false", "has_comments": "false", "preview_width": "127", "preview_height": "150"}, {"height": "4093", "score": "0", "file_url": "https://safebooru.org/images/3845/23ee22be19ab519c92c555b69ff69a9626e4ef08.jpg", "parent_id": "", "sample_url": "https://safebooru.org/samples/3845/sample_23ee22be19ab519c92c555b69ff69a9626e4ef08.jpg", "sample_width": "850", "sample_height": "1535", "preview_url": "https://safebooru.org/thumbnails/3845/thumbnail_23ee22be19ab519c92c555b69ff69a9626e4ef08.jpg", "rating": "s", "tags": " 1girl absurdres backpack bag bat_wings black_hair blue_archive choker collarbone commentary cowboy_shot ear_piercing gun h&k_usp handgun highres holding holding_gun holding_weapon hood hood_down hoodie horns jewelry kayoko_(blue_archive) laser_sight looking_at_viewer low_wings magazine_(weapon) miniskirt multicolored_hair necklace piercing pistol plaid plaid_skirt ponytail red_eyes reloading rotroto skirt solo standing suppressor trigger_discipline two-tone_hair weapon white_hair wings ", "id": "4016655", "width": "2267", "change": "1652992242", "md5": "ff56f6c92427796211682162cadff124", "creator_id": "168", "has_children": "false", "created_at": "Thu May 19 20:30:40 +0000 2022", "status": "active", "source": "https://i.pximg.net/img-original/img/2022/01/17/20/20/37/95593288_p0.jpg", "has_notes": "false", "has_comments": "false", "preview_width": "83", "preview_height": "150"}, {"height": "2048", "score": "0", "file_url": "https://safebooru.org/images/3845/dfc9c998cc804582780725ae833e35f59becf9c8.jpg", "parent_id": "", "sample_url": "https://safebooru.org/samples/3845/sample_dfc9c998cc804582780725ae833e35f59becf9c8.jpg", "sample_width": "850", "sample_height": "963", "preview_url": "https://safebooru.org/thumbnails/3845/thumbnail_dfc9c998cc804582780725ae833e35f59becf9c8.jpg", "rating": "s", "tags": " bangs bare_arms bare_shoulders black_choker black_headwear black_legwear blonde_hair blue_eyes blunt_bangs breasts choker clothing_cutout dress elesa_(pokemon) headphones highres navel navel_cutout pantyhose pokemon pokemon_(game) pokemon_bw short_dress short_hair skirt surumeika_(ninfiiiir) underbust yellow_dress yellow_skirt ", "id": "4016654", "width": "1808", "change": "1652992240", "md5": "1038e4a49e636694d76c56a1907b49c3", "creator_id": "168", "has_children": "false", "created_at": "Thu May 19 20:30:39 +0000 2022", "status": "active", "source": "https://i.pximg.net/img-original/img/2020/09/21/00/57/21/84505425_p1.jpg", "has_notes": "false", "has_comments": "false", "preview_width": "132", "preview_height": "150"}, {"height": "1331", "score": "0", "file_url": "https://safebooru.org/images/3845/832fe6a628e1b1b7f12e9573dbab1992cbc49611.jpg", "parent_id": "", "sample_url": "https://safebooru.org/images/3845/832fe6a628e1b1b7f12e9573dbab1992cbc49611.jpg", "sample_width": "1009", "sample_height": "1331", "preview_url": "https://safebooru.org/thumbnails/3845/thumbnail_832fe6a628e1b1b7f12e9573dbab1992cbc49611.jpg", "rating": "s", "tags": " 1girl animal_ear_fluff animal_ears bandage_over_one_eye bandaged_head bandages bed black_hair blue_eyes cat_ears cat_girl expressionless highres hospital_bed hospital_gown on_bed original satou_(3366_s) short_hair sketch sleeves_past_fingers sleeves_past_wrists stuffed_animal stuffed_cat stuffed_toy ", "id": "4016653", "width": "1009", "change": "1652992239", "md5": "83008d40df48ed82396a3bda009bc326", "creator_id": "168", "has_children": "false", "created_at": "Thu May 19 20:30:38 +0000 2022", "status": "active", "source": "https://twitter.com/kakusatou_3333/status/1488888367211110411", "has_notes": "false", "has_comments": "false", "preview_width": "113", "preview_height": "150"}, {"height": "4450", "score": "0", "file_url": "https://safebooru.org/images/3845/7122ff1fc0ac8774ba9cf04513dc8e503724198d.jpg", "parent_id": "", "sample_url": "https://safebooru.org/samples/3845/sample_7122ff1fc0ac8774ba9cf04513dc8e503724198d.jpg", "sample_width": "850", "sample_height": "1427", "preview_url": "https://safebooru.org/thumbnails/3845/thumbnail_7122ff1fc0ac8774ba9cf04513dc8e503724198d.jpg", "rating": "s", "tags": " 1girl absurdres bangs barefoot blonde_hair bodysuit closed_mouth elbow_gloves eyebrows_visible_through_hair feet full_body girls_frontline gloves grey_eyes highres holding holding_wand kolibri_(girls'_frontline) leggings lips long_hair looking_away pants qiye_jiexian simple_background sitting solo toes wand white_bodysuit white_gloves white_pants wide_sleeves ", "id": "4016652", "width": "2650", "change": "1652992238", "md5": "18818e1ccdf64f850ce1783ed728b93f", "creator_id": "168", "has_children": "false", "created_at": "Thu May 19 20:30:36 +0000 2022", "status": "active", "source": "https://i.pximg.net/img-original/img/2022/05/01/16/12/06/98017241_p0.jpg", "has_notes": "false", "has_comments": "false", "preview_width": "89", "preview_height": "150"}, {"height": "2004", "score": "0", "file_url": "https://safebooru.org/images/3845/3983a1aafe5dd87db3d447519020b45209982a75.jpg", "parent_id": "", "sample_url": "https://safebooru.org/samples/3845/sample_3983a1aafe5dd87db3d447519020b45209982a75.jpg", "sample_width": "850", "sample_height": "850", "preview_url": "https://safebooru.org/thumbnails/3845/thumbnail_3983a1aafe5dd87db3d447519020b45209982a75.jpg", "rating": "s", "tags": " close-up food food_focus highres leahgardnerart no_humans original shadow symbol-only_commentary tomato ", "id": "4016651", "width": "2004", "change": "1652992236", "md5": "61149772765de4c67dd62f0f29d8c616", "creator_id": "168", "has_children": "false", "created_at": "Thu May 19 20:30:35 +0000 2022", "status": "active", "source": "https://twitter.com/leahgardnerart/status/1527317428216397825", "has_notes": "false", "has_comments": "false", "preview_width": "150", "preview_height": "150"}]}}