{"posts": {"count": "3678556", "offset": "408", "post": [{"height": "1723", "score": "0", "file_url": "https://safebooru.org/images/3686/49d63671d035e6371737a518403177ec358fc914.png", "parent_id": "", "sample_url": "https://safebooru.org/samples/3686/sample_49d63671d035e6371737a518403177ec358fc914.jpg", "sample_width": "850", "sample_height": "1168", "preview_url": "https://safebooru.org/thumbnails/3686/thumbnail_49d63671d035e6371737a518403177ec358fc914.jpg", "rating": "s", "tags": " 1girl ;q akisa_(12023648) anchor black_gloves brown_hair fingerless_gloves gloves guilty_gear guilty_gear_strive hat highres holding holding_anchor jacket long_hair long_sleeves looking_at_viewer may_(guilty_gear) one_eye_closed orange_eyes orange_headwear orange_jacket pirate_hat simple_background skull_and_crossbones solo tongue tongue_out twitter_username white_background ", "id": "3848035", "width": "1254", "change": "1643992214", "md5": "f33f6cfde9cb84d4d3ddfd223d66f24d", "creator_id": "168", "has_children": "false", "created_at": "Fri Feb 04 16:30:14 +0000 2022", "status": "active", "source": "https://i.pximg.net/img-original/img/2022/02/05/00/57/12/96005669_p0.png", "has_notes": "false", "has_comments": "false", "preview_width": "109", "preview_height": "150"}, {"height": "2844", "score": "0", "file_url": "https://safebooru.org/images/3686/b55ed75ed323f7b2cb56373bc420d56699eeb065.jpg", "parent_id": "", "sample_url": "https://safebooru.org/samples/3686/sample_b55ed75ed323f7b2cb56373bc420d56699eeb065.jpg", "sample_width": "850", "sample_height": "1063", "preview_url": "https://safebooru.org/thumbnails/3686/thumbnail_b55ed75ed323f7b2cb56373bc420d56699eeb065.jpg", "rating": "s", "tags": " 2girls absurdres apple back-to-back bag black_shirt blue_eyes blue_hair blue_nails blue_skirt blueberry choker cuffs digimon digivice earrings eyewear_on_head flower food fruit full_body handcuffs heart high_heels highres interlocked_fingers jewelry long_hair looking_at_viewer magnet multiple_girls nail_polish original personification poke_ball pokemon red_eyes red_skirt redhead rinotuna shirt short_hair shoulder_bag skirt smile strawberry sunglasses t-shirt tattoo teeth thigh-highs upper_teeth white_background white_shirt ", "id": "3848034", "width": "2274", "change": "1643992213", "md5": "3fea3250e2148919f788308095c2fee6", "creator_id": "168", "has_children": "false", "created_at": "Fri Feb 04 16:30:12 +0000 2022", "status": "active", "source": "https://rinotuna.artstation.com/projects/eJPEW3", "has_notes": "false", "has_comments": "false", "preview_width": "119", "preview_height": "150"}, {"height": "3695", "score": "0", "file_url": "https://safebooru.org/images/3686/078c08e6413cf8c8b576331dfaf8e5c1e4128ba6.jpg", "parent_id": "", "sample_url": "https://safebooru.org/samples/3686/sample_078c08e6413cf8c8b576331dfaf8e5c1e4128ba6.jpg", "sample_width": "850", "sample_height": "1063", "preview_url": "https://safebooru.org/thumbnails/3686/thumbnail_078c08e6413cf8c8b576331dfaf8e5c1e4128ba6.jpg", "rating": "s", "tags": " 1boy absurdres adelie_penguin bear bird black_choker black_headwear black_jumpsuit choker highres jumpsuit looking_at_viewer male_focus muscular muscular_male o-ring o-ring_choker original penguin personification pink_footwear polar_bear rabbit rinotuna sandals seal_(animal) shadow solo standing tank_top tattoo tears white_tank_top ", "id": "3848033", "width": "2956", "change": "1643992212", "md5": "a6e2871036b2ec98d6bc470b3a5ce212", "creator_id": "168", "has_children": "false", "created_at": "Fri Feb 04 16:30:11 +0000 2022", "status": "active", "source": "https://rinotuna.artstation.com/projects/5BKk3A", "has_notes": "false", "has_comments": "false", "preview_width": "120", "preview_height": "150"}, {"height": "1199", "score": "0", "file_url": "https://safebooru.org/images/3686/fee086d8a88a7030cb563c4524b55359257042ea.jpg", "parent_id": "", "sample_url": "https://safebooru.org/images/3686/fee086d8a88a7030cb563c4524b55359257042ea.jpg", "sample_width": "848", "sample_height": "1199", "preview_url": "https://safebooru.org/thumbnails/3686/thumbnail_fee086d8a88a7030cb563c4524b55359257042ea.jpg", "rating": "s", "tags": " 1girl bangs coat fate/grand_order fate_(series) felnemo hair_between_eyes hair_ribbon hands_up horns looking_at_viewer open_clothes open_coat open_mouth orange_eyes own_hands_together pink_hair ribbon scarf smile snowflakes solo sweater tomoe_gozen_(fate) upper_body ", "id": "3848032", "width": "848", "change": "1643992210", "md5": "5070463bdbfbde37d60595f0da59a25e", "creator_id": "168", "has_children": "false", "created_at": "Fri Feb 04 16:30:10 +0000 2022", "status": "active", "source": "https://twitter.com/FelNeMo3/status/1489524833499348992", "has_notes": "false", "has_comments": "false", "preview_width": "106", "preview_height": "150"}, {"height": "960", "score": "0", "file_url": "https://safebooru.org/images/3686/85f62061aef93f4a8cee95927cc7a90cdfd4323e.jpg", "parent_id": "", "sample_url": "https://safebooru.org/samples/3686/sample_85f62061aef93f4a8cee95927cc7a90cdfd4323e.jpg", "sample_width": "850", "sample_height": "638", "preview_url": "https://safebooru.org/thumbnails/3686/thumbnail_85f62061aef93f4a8cee95927cc7a90cdfd4323e.jpg", "rating": "s", "tags": " 4girls bed bed_sheet blazer blush bow brown_hair brown_jacket closed_eyes closed_mouth doki_doki_literature_club hair_ornament hairclip half-closed_eyes head_on_another's_shoulder jacket leaning_on_person long_hair lying lying_on_person monika_(doki_doki_literature_club) multiple_girls natsuki_(doki_doki_literature_club) on_back open_mouth pink_hair ponytail purple_hair red_bow ribbon sayori_(doki_doki_literature_club) school_uniform short_hair sleeping sleeping_on_person sweat tsubobot twintails unconscious violet_eyes waking_up white_ribbon yuri_(doki_doki_literature_club) ", "id": "3848031", "width": "1280", "change": "1643992210", "md5": "7171a0707879f329e59d58809968e284", "creator_id": "168", "has_children": "false", "created_at": "Fri Feb 04 16:30:09 +0000 2022", "status": "active", "source": "https://twitter.com/jSY9emonizou/status/1489494083928084480", "has_notes": "false", "has_comments": "false", "preview_width": "150", "preview_height": "112"}, {"height": "692", "score": "0", "file_url": "https://safebooru.org/images/3686/2553f6ae725fc5b8bc42e656d169ee15cfd2f84d.jpg", "parent_id": "", "sample_url": "https://safebooru.org/images/3686/2553f6ae725fc5b8bc42e656d169ee15cfd2f84d.jpg", "sample_width": "1000", "sample_height": "692", "preview_url": "https://safebooru.org/thumbnails/3686/thumbnail_2553f6ae725fc5b8bc42e656d169ee15cfd2f84d.jpg", "rating": "s", "tags": " 2girls black_hair bowl chopsticks duplicate eating fake_horns food green_eyes hair_ribbon headgear holding holding_chopsticks horned_headwear horns i-203_(kancolle) i-47_(kancolle) kantai_collection kotatsu light_blue_eyes light_blue_hair long_hair low-tied_long_hair masara_(chuujou) multiple_girls neckerchief nontraditional_school_swimsuit noodles pixel-perfect_duplicate ramen ribbon sailor_collar school_swimsuit sidelocks swimsuit table tress_ribbon white_neckerchief white_sailor_collar yura_(kancolle) ", "id": "3848030", "width": "1000", "change": "1643992208", "md5": "1ed260885b3f20eaed3f065a7300b0fb", "creator_id": "168", "has_children": "false", "created_at": "Fri Feb 04 16:30:08 +0000 2022", "status": "active", "source": "https://i.pximg.net/img-original/img/2022/02/05/01/11/42/96005978_p0.jpg", "has_notes": "false", "has_comments": "false", "preview_width": "150", "preview_height": "103"}, {"height": "1012", "score": "0", "file_url": "https://safebooru.org/images/3686/703a0b430ce142bb43f000bed6f4d4284850c10f.jpg", "parent_id": "", "sample_url": "https://safebooru.org/images/3686/703a0b430ce142bb43f000bed6f4d4284850c10f.jpg", "sample_width": "717", "sample_height": "1012", "preview_url": "https://safebooru.org/thumbnails/3686/thumbnail_703a0b430ce142bb43f000bed6f4d4284850c10f.jpg", "rating": "s", "tags": " 1girl animal_print bangs beans bikini blue_eyes blue_hair commentary_request gradient_hair grey_background horns hugging_own_legs kantai_collection long_hair mae_(maesanpicture) multicolored_hair oni_horns samidare_(kancolle) simple_background sitting solo spoken_sweatdrop strapless strapless_bikini sweatdrop swept_bangs swimsuit thigh-highs tiger_print very_long_hair yellow_bikini yellow_legwear ", "id": "3848029", "width": "717", "change": "1643992207", "md5": "41aa0d8cecaffaea7971c7f0fcbb14e6", "creator_id": "168", "has_children": "false", "created_at": "Fri Feb 04 16:30:07 +0000 2022", "status": "active", "source": "https://twitter.com/maesanpicture/status/1489251145809731600", "has_notes": "false", "has_comments": "false", "preview_width": "106", "preview_height": "150"}, {"height": "2000", "score": "0", "file_url": "https://safebooru.org/images/3686/9aa9b4ffd602b078f634badb442b9bd779d6f988.jpg", "parent_id": "", "sample_url": "https://safebooru.org/samples/3686/sample_9aa9b4ffd602b078f634badb442b9bd779d6f988.jpg", "sample_width": "850", "sample_height": "1200", "preview_url": "https://safebooru.org/thumbnails/3686/thumbnail_9aa9b4ffd602b078f634badb442b9bd779d6f988.jpg", "rating": "s", "tags": " 1girl 774_inc. belt black_ribbon blue_hair blue_skirt blush brown_belt closed_mouth green_hair hair_ribbon hand_on_hip highres hiyoku_no_crosspiece hoppege jacket long_sleeves looking_at_viewer midriff mole mole_under_eye multicolored_hair navel red_eyes ribbon skirt smile solo standing suzumi_nemo two-tone_hair white_jacket ", "id": "3848028", "width": "1417", "change": "1643992207", "md5": "c654c8f95c4acc142c14ff38790acb80", "creator_id": "168", "has_children": "false", "created_at": "Fri Feb 04 16:30:05 +0000 2022", "status": "active", "source": "https://i.pximg.net/img-original/img/2022/02/05/01/18/33/96006116_p0.jpg", "has_notes": "false", "has_comments": "false", "preview_width": "106", "preview_height": "150"}, {"height": "1600", "score": "0", "file_url": "https://safebooru.org/images/3686/a6bc5d93fba140bbbcc0b49b87c59474398ef994.jpg", "parent_id": "", "sample_url": "https://safebooru.org/samples/3686/sample_a6bc5d93fba140bbbcc0b49b87c59474398ef994.jpg", "sample_width": "850", "sample_height": "1133", "preview_url": "https://safebooru.org/thumbnails/3686/thumbnail_a6bc5d93fba140bbbcc0b49b87c59474398ef994.jpg", "rating": "s", "tags": " 1girl ahoge akebono_(kancolle) bell blue_sailor_collar blue_skirt blue_sweater box commentary_request dated flower hair_bell hair_flower hair_ornament heart highres jingle_bell kantai_collection long_hair looking_at_viewer one-hour_drawing_challenge pleated_skirt purple_hair sailor_collar sawatani_(chevalier_04056) school_uniform serafuku side_ponytail simple_background skirt solo standing sweater twitter_username very_long_hair violet_eyes white_background ", "id": "3848027", "width": "1200", "change": "1643992205", "md5": "e0a1d539c96cf9ddd8e0dd9441bb52ab", "creator_id": "168", "has_children": "false", "created_at": "Fri Feb 04 16:30:04 +0000 2022", "status": "active", "source": "https://twitter.com/Chevalier_04056/status/1488898083844808710", "has_notes": "false", "has_comments": "false", "preview_width": "112", "preview_height": "150"}, {"height": "2023", "score": "0", "file_url": "https://safebooru.org/images/3686/f6c8401b2eb40ca49db05d0268e50c066e2eafd9.png", "parent_id": "", "sample_url": "https://safebooru.org/samples/3686/sample_f6c8401b2eb40ca49db05d0268e50c066e2eafd9.jpg", "sample_width": "850", "sample_height": "1209", "preview_url": "https://safebooru.org/thumbnails/3686/thumbnail_f6c8401b2eb40ca49db05d0268e50c066e2eafd9.jpg", "rating": "s", "tags": " 1girl armpits ascot bow breasts brown_eyes brown_hair detached_sleeves frilled_bow frills hair_bow hair_tubes hakurei_reimu highres kanpa_(campagne_9) medium_hair nontraditional_miko ofuda outstretched_arms pillow red_bow red_skirt ribbon-trimmed_sleeves ribbon_trim skirt skirt_set small_breasts solo spread_arms touhou wide_sleeves yellow_ascot ", "id": "3848026", "width": "1422", "change": "1643990471", "md5": "a45718f26bc9c7dbe6c6db31dfdf31ef", "creator_id": "168", "has_children": "false", "created_at": "Fri Feb 04 16:01:10 +0000 2022", "status": "active", "source": "https://i.pximg.net/img-original/img/2021/05/01/09/21/48/89507869_p0.png", "has_notes": "false", "has_comments": "false", "preview_width": "105", "preview_height": "150"}, {"height": "2145", "score": "0", "file_url": "https://safebooru.org/images/3686/d2cdf3f6bea9929cebcd196ea72c1322e0fc5e7c.png", "parent_id": "", "sample_url": "https://safebooru.org/samples/3686/sample_d2cdf3f6bea9929cebcd196ea72c1322e0fc5e7c.jpg", "sample_width": "850", "sample_height": "1299", "preview_url": "https://safebooru.org/thumbnails/3686/thumbnail_d2cdf3f6bea9929cebcd196ea72c1322e0fc5e7c.jpg", "rating": "s", "tags": " 1girl bangs black_hair black_neckwear black_ribbon black_skirt border breasts closed_mouth clouds day eyebrows_visible_through_hair gradient gradient_background hat highres kanpa_(campagne_9) light_blush light_smile looking_at_viewer medium_breasts outside_border pointy_ears pom_pom_(clothes) red_eyes red_headwear ribbon shameimaru_aya shirt short_hair simple_background skirt sky solo tokin_hat touhou upper_body white_border white_shirt ", "id": "3848025", "width": "1404", "change": "1643990470", "md5": "b66af6f8b0d4e3004599f40998d93863", "creator_id": "168", "has_children": "false", "created_at": "Fri Feb 04 16:01:09 +0000 2022", "status": "active", "source": "https://i.pximg.net/img-original/img/2021/05/01/09/21/48/89507869_p2.png", "has_notes": "false", "has_comments": "false", "preview_width": "98", "preview_height": "150"}, {"height": "1426", "score": "0", "file_url": "https://safebooru.org/images/3686/53c5169bf14a0f935a73c9ce7e0057a0829e3aa4.png", "parent_id": "", "sample_url": "https://safebooru.org/images/3686/53c5169bf14a0f935a73c9ce7e0057a0829e3aa4.png", "sample_width": "1018", "sample_height": "1426", "preview_url": "https://safebooru.org/thumbnails/3686/thumbnail_53c5169bf14a0f935a73c9ce7e0057a0829e3aa4.jpg", "rating": "s", "tags": " 1girl bangs black_bow black_hair black_neckwear bow closed_mouth collar eyebrows_visible_through_hair hand_up hat highres holding kanpa_(campagne_9) looking_at_viewer pom_pom_(clothes) puffy_short_sleeves puffy_sleeves red_eyes red_headwear shameimaru_aya shirt short_hair short_sleeves simple_background smile solo tokin_hat touhou white_background white_collar white_shirt white_sleeves ", "id": "3848024", "width": "1018", "change": "1643990469", "md5": "81fa48c9ae0e6e9356d7e1a134e54c4e", "creator_id": "168", "has_children": "false", "created_at": "Fri Feb 04 16:01:08 +0000 2022", "status": "active", "source": "https://i.pximg.net/img-original/img/2021/05/01/09/21/48/89507869_p3.png", "has_notes": "false", "has_comments": "false", "preview_width": "107", "preview_height": "150"}]}}