{"posts": {"count": "3777297", "offset": "636", "post": [{"height": "2546", "score": "0", "file_url": "https://safebooru.org/images/3784/13bfd0e8c723336585630880e8532f0b6229034d.jpg", "parent_id": "", "sample_url": "https://safebooru.org/samples/3784/sample_13bfd0e8c723336585630880e8532f0b6229034d.jpg", "sample_width": "850", "sample_height": "478", "preview_url": "https://safebooru.org/thumbnails/3784/thumbnail_13bfd0e8c723336585630880e8532f0b6229034d.jpg", "rating": "s", "tags": " 1girl absurdres african_penguin_(kemono_friends) animal_ears black_eyes black_gloves black_hair gloves highres kemono_friends kemono_friends_v_project long_hair looking_at_viewer multicolored_hair necktie noginogiro shirt shoes simple_background skirt smile solo tail virtual_youtuber white_shirt ", "id": "3952649", "width": "4523", "change": "1649764827", "md5": "be05d09a5e327a01a19eaee1c13e77c0", "creator_id": "168", "has_children": "false", "created_at": "Tue Apr 12 12:00:25 +0000 2022", "status": "active", "source": "https://i.pximg.net/img-original/img/2022/03/23/21/30/19/97124562_p0.jpg", "has_notes": "false", "has_comments": "false", "preview_width": "150", "preview_height": "84"}, {"height": "1399", "score": "0", "file_url": "https://safebooru.org/images/3784/02ee9ed03cf280e7e206caf924fb6f32705d9a95.jpg", "parent_id": "", "sample_url": "https://safebooru.org/images/3784/02ee9ed03cf280e7e206caf924fb6f32705d9a95.jpg", "sample_width": "951", "sample_height": "1399", "preview_url": "https://safebooru.org/thumbnails/3784/thumbnail_02ee9ed03cf280e7e206caf924fb6f32705d9a95.jpg", "rating": "s", "tags": " 2girls animal_ear_fluff animal_ears arms_up barefoot bed bedroom blue_dress blue_eyes blue_nightgown blush bow breasts brown_hair camisole cardigan cat_ears cat_girl cat_tail cat_teaser curtains dress face-to-face grabbing grabbing_from_behind hair_bow hair_ornament hairclip highres holding_hands indoors kneeling long_hair multiple_girls nightgown off_shoulder one_side_up open_mouth original pillow pink_camisole pink_eyes pink_hair pink_shorts poncho_(31103105) ribbon short_dress short_hair short_shorts shorts smile socks striped striped_cardigan striped_footwear tail tail_wrap thighs twintails window yuri ", "id": "3952648", "width": "951", "change": "1649764825", "md5": "ab9552d44fb93412a63bed717ebdc7e1", "creator_id": "168", "has_children": "false", "created_at": "Tue Apr 12 12:00:24 +0000 2022", "status": "active", "source": "https://twitter.com/komarii_/status/1498147948290797569", "has_notes": "false", "has_comments": "false", "preview_width": "101", "preview_height": "150"}, {"height": "2048", "score": "0", "file_url": "https://safebooru.org/images/3784/f2d72551caad31e3c845481c5bcfabd2eb3f7175.jpg", "parent_id": "", "sample_url": "https://safebooru.org/images/3784/f2d72551caad31e3c845481c5bcfabd2eb3f7175.jpg", "sample_width": "1336", "sample_height": "2048", "preview_url": "https://safebooru.org/thumbnails/3784/thumbnail_f2d72551caad31e3c845481c5bcfabd2eb3f7175.jpg", "rating": "s", "tags": " 1girl blue_eyes dress flower highres holding kyomunohi lily_white long_hair long_sleeves orange_hair rose solo touhou white_dress white_headwear wings ", "id": "3952647", "width": "1336", "change": "1649764823", "md5": "b8d1ad99d4408241bdb7bffd909bced7", "creator_id": "168", "has_children": "false", "created_at": "Tue Apr 12 12:00:23 +0000 2022", "status": "active", "source": "https://i.pximg.net/img-original/img/2022/04/12/20/04/24/97583335_p0.jpg", "has_notes": "false", "has_comments": "false", "preview_width": "97", "preview_height": "150"}, {"height": "1867", "score": "0", "file_url": "https://safebooru.org/images/3784/8567be3762a0ff86ecc74582067842b4e8d622c7.jpg", "parent_id": "", "sample_url": "https://safebooru.org/samples/3784/sample_8567be3762a0ff86ecc74582067842b4e8d622c7.jpg", "sample_width": "850", "sample_height": "815", "preview_url": "https://safebooru.org/thumbnails/3784/thumbnail_8567be3762a0ff86ecc74582067842b4e8d622c7.jpg", "rating": "s", "tags": " 1girl :d ahoge animal_ears bangs black_collar black_hoodie cat_ears cat_girl cat_tail closed_eyes collar cropped_hoodie eyebrows_visible_through_hair hair_between_eyes highres hololive hood hoodie indian_style looking_at_viewer medium_hair midriff nekomata_okayu nyan pants purple_hair ruka_tou shoes sitting smile tail v_arms violet_eyes virtual_youtuber white_pants ", "id": "3952646", "width": "1948", "change": "1649764822", "md5": "7f7268adc4c5d1a9e396be3830f2145f", "creator_id": "168", "has_children": "false", "created_at": "Tue Apr 12 12:00:22 +0000 2022", "status": "active", "source": "https://twitter.com/ruka_tou/status/1511282539226603523", "has_notes": "false", "has_comments": "false", "preview_width": "150", "preview_height": "143"}, {"height": "1024", "score": "0", "file_url": "https://safebooru.org/images/3784/52216ccd38c218993879f075bfb621d879212e6f.jpg", "parent_id": "", "sample_url": "https://safebooru.org/images/3784/52216ccd38c218993879f075bfb621d879212e6f.jpg", "sample_width": "622", "sample_height": "1024", "preview_url": "https://safebooru.org/thumbnails/3784/thumbnail_52216ccd38c218993879f075bfb621d879212e6f.jpg", "rating": "s", "tags": " 1girl ahoge animal_ear_fluff animal_ears bangs black_collar black_hoodie cat_ears cat_girl cat_tail closed_mouth collar eyebrows_visible_through_hair hololive hood hoodie looking_at_viewer nekomata_okayu purple_hair ruka_tou short_hair simple_background smile solo tail upper_body violet_eyes virtual_youtuber white_background ", "id": "3952645", "width": "622", "change": "1649764821", "md5": "087c91e81884172f1c2139dc4f96dae0", "creator_id": "168", "has_children": "false", "created_at": "Tue Apr 12 12:00:21 +0000 2022", "status": "active", "source": "https://twitter.com/ruka_tou/status/1513834744911626241", "has_notes": "false", "has_comments": "false", "preview_width": "91", "preview_height": "150"}, {"height": "1765", "score": "0", "file_url": "https://safebooru.org/images/3784/5f5f29c7d7c6beb8275b81c8ef744c5b60bcd350.jpg", "parent_id": "", "sample_url": "https://safebooru.org/samples/3784/sample_5f5f29c7d7c6beb8275b81c8ef744c5b60bcd350.jpg", "sample_width": "850", "sample_height": "733", "preview_url": "https://safebooru.org/thumbnails/3784/thumbnail_5f5f29c7d7c6beb8275b81c8ef744c5b60bcd350.jpg", "rating": "s", "tags": " 1girl ;) ahoge animal_ear_fluff animal_ears bangs black_collar cat_ears cat_girl cat_tail collar eyebrows_visible_through_hair grin headphones headphones_around_neck highres hololive long_sleeves looking_at_viewer multiple_views neck_ribbon nekomata_okayu one_eye_closed parted_lips purple_hair ribbon ruka_tou shirt short_hair smile tail violet_eyes virtual_youtuber white_shirt ", "id": "3952644", "width": "2048", "change": "1649764821", "md5": "638e302b298809dbf52b83c2f46dbdd6", "creator_id": "168", "has_children": "false", "created_at": "Tue Apr 12 12:00:20 +0000 2022", "status": "active", "source": "https://twitter.com/ruka_tou/status/1513473193025347584", "has_notes": "false", "has_comments": "false", "preview_width": "150", "preview_height": "129"}, {"height": "1798", "score": "0", "file_url": "https://safebooru.org/images/3784/cb633b1db9e352bc786f1fd4bd3d5ca8f36ebe21.jpg", "parent_id": "", "sample_url": "https://safebooru.org/images/3784/cb633b1db9e352bc786f1fd4bd3d5ca8f36ebe21.jpg", "sample_width": "1280", "sample_height": "1798", "preview_url": "https://safebooru.org/thumbnails/3784/thumbnail_cb633b1db9e352bc786f1fd4bd3d5ca8f36ebe21.jpg", "rating": "s", "tags": " animal_ears cat cat_ears cat_tail cover cover_page doujin_cover futa_(nabezoko) hakurei_reimu hat highres looking_at_viewer red_eyes sweat tail touhou ", "id": "3952643", "width": "1280", "change": "1649764820", "md5": "b01ee8733aa19dc72ab99f7ae58d3a80", "creator_id": "168", "has_children": "false", "created_at": "Tue Apr 12 12:00:19 +0000 2022", "status": "active", "source": "https://e-hentai.org/s/6268ec1f5f/958356-1", "has_notes": "false", "has_comments": "false", "preview_width": "106", "preview_height": "150"}, {"height": "1844", "score": "0", "file_url": "https://safebooru.org/images/3784/ab8c0c80f1a7c366a5592a94aa88fc08671a56e0.jpg", "parent_id": "", "sample_url": "https://safebooru.org/samples/3784/sample_ab8c0c80f1a7c366a5592a94aa88fc08671a56e0.jpg", "sample_width": "850", "sample_height": "1225", "preview_url": "https://safebooru.org/thumbnails/3784/thumbnail_ab8c0c80f1a7c366a5592a94aa88fc08671a56e0.jpg", "rating": "s", "tags": " animal_ears aura blank_eyes cat_ears cat_girl cat_tail chen fox_tail futa_(nabezoko) greyscale hat highres looking_back monochrome tail touhou waking_up yakumo_ran yakumo_yukari ", "id": "3952642", "width": "1280", "change": "1649764819", "md5": "ab9127b2e9e0170e413b890660ad81e8", "creator_id": "168", "has_children": "false", "created_at": "Tue Apr 12 12:00:18 +0000 2022", "status": "active", "source": "https://e-hentai.org/s/871f0daf5b/958356-10", "has_notes": "false", "has_comments": "false", "preview_width": "104", "preview_height": "150"}, {"height": "1800", "score": "0", "file_url": "https://safebooru.org/images/3784/69ed6545de4c828eb1841df21514caed5392c384.jpg", "parent_id": "", "sample_url": "https://safebooru.org/samples/3784/sample_69ed6545de4c828eb1841df21514caed5392c384.jpg", "sample_width": "850", "sample_height": "1020", "preview_url": "https://safebooru.org/thumbnails/3784/thumbnail_69ed6545de4c828eb1841df21514caed5392c384.jpg", "rating": "s", "tags": " 1girl bianca_(dq5) blonde_hair blue_eyes blush braid cape choker closed_mouth collarbone dragon_quest dragon_quest_v earrings hair_over_shoulder hair_ribbon highres isa_(chiyo-s) jewelry long_hair orange_cape profile ribbon single_braid solo white_background ", "id": "3952641", "width": "1500", "change": "1649764818", "md5": "9eefd451f5e2d886f04a39190064f772", "creator_id": "168", "has_children": "false", "created_at": "Tue Apr 12 12:00:17 +0000 2022", "status": "active", "source": "https://twitter.com/bm_i3/status/1139809019285999621", "has_notes": "false", "has_comments": "false", "preview_width": "125", "preview_height": "150"}, {"height": "768", "score": "0", "file_url": "https://safebooru.org/images/3784/3d8a235ae69e9a17076e476a93f5469376eaaa11.jpg", "parent_id": "", "sample_url": "https://safebooru.org/images/3784/3d8a235ae69e9a17076e476a93f5469376eaaa11.jpg", "sample_width": "1024", "sample_height": "768", "preview_url": "https://safebooru.org/thumbnails/3784/thumbnail_3d8a235ae69e9a17076e476a93f5469376eaaa11.jpg", "rating": "s", "tags": " 2girls arms_around_neck au_ra avatar_(ff14) bangs closed_eyes commentary dragon_horns facing_viewer final_fantasy final_fantasy_xiv flower glowing_flower hair_flower hair_ornament holding holding_flower horns hug long_hair mask mask_removed multiple_girls night outdoors scales sky smile standing star_(sky) starry_sky upper_body venat_(ff14) white_hair white_robe xiaoli_(1507) ", "id": "3952640", "width": "1024", "change": "1649764817", "md5": "846ad4f262aa05237e6081ac8ee31645", "creator_id": "168", "has_children": "false", "created_at": "Tue Apr 12 12:00:16 +0000 2022", "status": "active", "source": "https://i.pximg.net/img-original/img/2022/04/12/00/10/00/97569357_p0.jpg", "has_notes": "false", "has_comments": "false", "preview_width": "150", "preview_height": "112"}, {"height": "1571", "score": "", "file_url": "https://safebooru.org/images/3784/f476010221d9477665ff48cbdf2a7d8fc4bbb1b5.jpg", "parent_id": "", "sample_url": "https://safebooru.org/images/3784/f476010221d9477665ff48cbdf2a7d8fc4bbb1b5.jpg", "sample_width": "900", "sample_height": "1571", "preview_url": "https://safebooru.org/thumbnails/3784/thumbnail_f476010221d9477665ff48cbdf2a7d8fc4bbb1b5.jpg", "rating": "s", "tags": " 1girl blue_swimsuit blush brown_hair commission covered_navel grey_background hands_on_own_chest highres long_hair looking_at_viewer matchanear name_tag one-piece_swimsuit original own_hands_together ponytail red_eyes school_swimsuit scrunchie simple_background skeb_commission solo swimsuit thighs ", "id": "3952639", "width": "900", "change": "1649764816", "md5": "facf12b4cd0c04b2a7e0e1947d80fd3e", "creator_id": "168", "has_children": "false", "created_at": "Tue Apr 12 12:00:16 +0000 2022", "status": "active", "source": "https://twitter.com/MatchaNear/status/1441336415166472194", "has_notes": "false", "has_comments": "false", "preview_width": "85", "preview_height": "150"}, {"height": "1770", "score": "0", "file_url": "https://safebooru.org/images/3784/ae79a90c839d5ff33cc34ae7709de3ed2c2991e7.jpg", "parent_id": "", "sample_url": "https://safebooru.org/images/3784/ae79a90c839d5ff33cc34ae7709de3ed2c2991e7.jpg", "sample_width": "1253", "sample_height": "1770", "preview_url": "https://safebooru.org/thumbnails/3784/thumbnail_ae79a90c839d5ff33cc34ae7709de3ed2c2991e7.jpg", "rating": "s", "tags": " 1girl alternate_costume alternate_wings asameshi bangs blonde_hair box flandre_scarlet hair_between_eyes hair_ribbon hands_up heart heart-shaped_box highres holding hood hoodie long_sleeves looking_at_viewer medium_hair no_hat no_headwear one_side_up pink_background red_eyes red_hoodie red_ribbon ribbon solo touhou upper_body wings ", "id": "3952638", "width": "1253", "change": "1649764816", "md5": "84e4d757fc1282ae94216d4560d6eaeb", "creator_id": "168", "has_children": "false", "created_at": "Tue Apr 12 12:00:15 +0000 2022", "status": "active", "source": "https://twitter.com/a0_0san/status/1493239664689385474", "has_notes": "false", "has_comments": "false", "preview_width": "106", "preview_height": "150"}]}}