{"posts": {"count": "3585232", "offset": "96", "post": [{"height": "1350", "score": "0", "file_url": "https://safebooru.org/images/3618/d74b40ea1b20eb768b707a5d6c1fe2496697cc32.jpg", "parent_id": "", "sample_url": "https://safebooru.org/samples/3618/sample_d74b40ea1b20eb768b707a5d6c1fe2496697cc32.jpg", "sample_width": "850", "sample_height": "560", "preview_url": "https://safebooru.org/thumbnails/3618/thumbnail_d74b40ea1b20eb768b707a5d6c1fe2496697cc32.jpg", "rating": "s", "tags": " 2girls arms_up black_sailor_collar blue_hair covered_face crescent_moon hair_over_face highres long_hair long_sleeves medium_hair moon multiple_girls neckerchief original ponytail purple_hair rasukusekai red_neckerchief sailor_collar shirt sparkle upper_body white_shirt ", "id": "3775427", "width": "2048", "change": "1640298721", "md5": "89a5a5d08508a81431654eb485dba055", "creator_id": "168", "has_children": "false", "created_at": "Thu Dec 23 22:32:01 +0000 2021", "status": "active", "source": "https://twitter.com/hun5751/status/1346435330006679552", "has_notes": "false", "has_comments": "false", "preview_width": "150", "preview_height": "98"}, {"height": "2048", "score": "0", "file_url": "https://safebooru.org/images/3618/405101b6fc380189ff3fc12591416df77a77e510.jpg", "parent_id": "", "sample_url": "https://safebooru.org/samples/3618/sample_405101b6fc380189ff3fc12591416df77a77e510.jpg", "sample_width": "850", "sample_height": "850", "preview_url": "https://safebooru.org/thumbnails/3618/thumbnail_405101b6fc380189ff3fc12591416df77a77e510.jpg", "rating": "s", "tags": " 1girl blue_sailor_collar brown_hair clouds curtains facing_away from_side halo hand_up highres neckerchief original purple_theme rasukusekai red_neckerchief sailor_collar shadow shirt short_hair short_sleeves solo upper_body white_shirt window ", "id": "3775426", "width": "2048", "change": "1640298721", "md5": "daefe98c2f5b311d7e9f5d21bf49a771", "creator_id": "168", "has_children": "false", "created_at": "Thu Dec 23 22:32:00 +0000 2021", "status": "active", "source": "https://twitter.com/hun5751/status/1346759781936103424", "has_notes": "false", "has_comments": "false", "preview_width": "150", "preview_height": "150"}, {"height": "2048", "score": "0", "file_url": "https://safebooru.org/images/3618/189edab6f1b4e9c360b20341141d5fd71affb505.jpg", "parent_id": "", "sample_url": "https://safebooru.org/samples/3618/sample_189edab6f1b4e9c360b20341141d5fd71affb505.jpg", "sample_width": "850", "sample_height": "850", "preview_url": "https://safebooru.org/thumbnails/3618/thumbnail_189edab6f1b4e9c360b20341141d5fd71affb505.jpg", "rating": "s", "tags": " 2girls aqua_sailor_collar blue_background blue_shirt blue_vest blush brown_hair chromatic_aberration curtains hand_up highres kiss long_hair long_sleeves multiple_girls original pink_shirt rasukusekai shadow shirt simple_background sparkle vest yuri ", "id": "3775425", "width": "2048", "change": "1640298720", "md5": "538e569bf46f1a5dbe78fdc0817eb4b5", "creator_id": "168", "has_children": "false", "created_at": "Thu Dec 23 22:31:59 +0000 2021", "status": "active", "source": "https://twitter.com/hun5751/status/1348933215730298880", "has_notes": "false", "has_comments": "false", "preview_width": "150", "preview_height": "150"}, {"height": "2048", "score": "0", "file_url": "https://safebooru.org/images/3618/aa48bec4fde30bf8d863558d53ef1e0082769571.jpg", "parent_id": "", "sample_url": "https://safebooru.org/samples/3618/sample_aa48bec4fde30bf8d863558d53ef1e0082769571.jpg", "sample_width": "850", "sample_height": "850", "preview_url": "https://safebooru.org/thumbnails/3618/thumbnail_aa48bec4fde30bf8d863558d53ef1e0082769571.jpg", "rating": "s", "tags": " 1girl aqua_hair armpits blush dew_drop eating facing_away food highres holding holding_food jewelry leaf long_hair necklace original plant popsicle portrait rasukusekai solo sparkle water_drop ", "id": "3775424", "width": "2048", "change": "1640298719", "md5": "1d132b3a8ea06218229e859ec6237dd8", "creator_id": "168", "has_children": "false", "created_at": "Thu Dec 23 22:31:58 +0000 2021", "status": "active", "source": "https://twitter.com/hun5751/status/1349689897456582659", "has_notes": "false", "has_comments": "false", "preview_width": "150", "preview_height": "150"}, {"height": "1440", "score": "0", "file_url": "https://safebooru.org/images/3618/42a77ce9b7f5b2f7967c0695d77adb1cb03e169f.jpg", "parent_id": "", "sample_url": "https://safebooru.org/samples/3618/sample_42a77ce9b7f5b2f7967c0695d77adb1cb03e169f.jpg", "sample_width": "850", "sample_height": "598", "preview_url": "https://safebooru.org/thumbnails/3618/thumbnail_42a77ce9b7f5b2f7967c0695d77adb1cb03e169f.jpg", "rating": "s", "tags": " 2girls black_hair black_shinkalion_berserker_mode blue_shirt bone cake candle english_text eyebrows_visible_through_hair flower food fruit gun highres long_hair multiple_girls original petals plate rasukusekai redhead shirt skull sparkle strawberry weapon yellow_flower yuri ", "id": "3775423", "width": "2048", "change": "1640298718", "md5": "05dbe1a51e0db7c01cbf54364f3e6ac5", "creator_id": "168", "has_children": "false", "created_at": "Thu Dec 23 22:31:57 +0000 2021", "status": "active", "source": "https://twitter.com/hun5751/status/1350819665040183299", "has_notes": "false", "has_comments": "false", "preview_width": "150", "preview_height": "105"}, {"height": "1352", "score": "0", "file_url": "https://safebooru.org/images/3618/5542ca4c1023703facba4e1476178145d12d384e.jpg", "parent_id": "", "sample_url": "https://safebooru.org/samples/3618/sample_5542ca4c1023703facba4e1476178145d12d384e.jpg", "sample_width": "850", "sample_height": "561", "preview_url": "https://safebooru.org/thumbnails/3618/thumbnail_5542ca4c1023703facba4e1476178145d12d384e.jpg", "rating": "s", "tags": " 1girl bendy_straw blue_hairband blue_shirt brown_hair collared_shirt cup drinking_straw feet_out_of_frame fork hairband highres holding holding_cup leaf long_hair long_sleeves original pink_skirt plant plate rasukusekai shirt skirt solo ", "id": "3775422", "width": "2048", "change": "1640298717", "md5": "ed49c472efb3504e711237ecdccd91f5", "creator_id": "168", "has_children": "false", "created_at": "Thu Dec 23 22:31:56 +0000 2021", "status": "active", "source": "https://twitter.com/hun5751/status/1351501182762586115", "has_notes": "false", "has_comments": "false", "preview_width": "150", "preview_height": "99"}, {"height": "2048", "score": "0", "file_url": "https://safebooru.org/images/3618/0022019b815db76fed4cd84908d86e7fa3c9b8bf.jpg", "parent_id": "", "sample_url": "https://safebooru.org/samples/3618/sample_0022019b815db76fed4cd84908d86e7fa3c9b8bf.jpg", "sample_width": "850", "sample_height": "1063", "preview_url": "https://safebooru.org/thumbnails/3618/thumbnail_0022019b815db76fed4cd84908d86e7fa3c9b8bf.jpg", "rating": "s", "tags": " 1girl arms_up blue_background blue_hair cowboy_shot from_behind grey_sailor_collar grey_skirt highres long_hair original pleated_skirt rainbow rasukusekai sailor_collar shadow shirt short_sleeves skirt solo sparkle white_shirt ", "id": "3775421", "width": "1638", "change": "1640298716", "md5": "b9b511b020fc871b2b3eaa4827fbdf5d", "creator_id": "168", "has_children": "false", "created_at": "Thu Dec 23 22:31:55 +0000 2021", "status": "active", "source": "https://twitter.com/hun5751/status/1353644951809101825", "has_notes": "false", "has_comments": "false", "preview_width": "119", "preview_height": "150"}, {"height": "2048", "score": "0", "file_url": "https://safebooru.org/images/3618/66c6853fb36251a9fee1318dde9a3e8df86d3b94.jpg", "parent_id": "", "sample_url": "https://safebooru.org/images/3618/66c6853fb36251a9fee1318dde9a3e8df86d3b94.jpg", "sample_width": "1154", "sample_height": "2048", "preview_url": "https://safebooru.org/thumbnails/3618/thumbnail_66c6853fb36251a9fee1318dde9a3e8df86d3b94.jpg", "rating": "s", "tags": " bottle chromatic_aberration english_text hands highres no_humans original partially_submerged perfume_bottle petals purple_theme rasukusekai shadow sparkle ", "id": "3775420", "width": "1154", "change": "1640298715", "md5": "9eac880570442de11776abd33f4c5654", "creator_id": "168", "has_children": "false", "created_at": "Thu Dec 23 22:31:55 +0000 2021", "status": "active", "source": "https://twitter.com/hun5751/status/1354377679177441280", "has_notes": "false", "has_comments": "false", "preview_width": "84", "preview_height": "150"}, {"height": "1280", "score": "0", "file_url": "https://safebooru.org/images/3618/c02bf0d5f56d77f24ec1ced25b8fca587cadf21d.jpg", "parent_id": "", "sample_url": "https://safebooru.org/samples/3618/sample_c02bf0d5f56d77f24ec1ced25b8fca587cadf21d.jpg", "sample_width": "850", "sample_height": "531", "preview_url": "https://safebooru.org/thumbnails/3618/thumbnail_c02bf0d5f56d77f24ec1ced25b8fca587cadf21d.jpg", "rating": "s", "tags": " 1girl aqua_hair black_eyes camera collared_shirt hand_up heart highres leaf long_hair long_sleeves mask mirror moon_phases mouth_mask original pink_mask plant portrait purple_shirt rasukusekai shadow shirt shooting_star solo sticker ", "id": "3775419", "width": "2048", "change": "1640298714", "md5": "ebde0493cb3ddfae7ecd72f089aa8b8d", "creator_id": "168", "has_children": "false", "created_at": "Thu Dec 23 22:31:54 +0000 2021", "status": "active", "source": "https://twitter.com/hun5751/status/1353325509971591168", "has_notes": "false", "has_comments": "false", "preview_width": "150", "preview_height": "93"}, {"height": "1544", "score": "0", "file_url": "https://safebooru.org/images/3618/84e0a456dbdcff9a65c202165ff891a6ebabe434.jpg", "parent_id": "", "sample_url": "https://safebooru.org/samples/3618/sample_84e0a456dbdcff9a65c202165ff891a6ebabe434.jpg", "sample_width": "850", "sample_height": "641", "preview_url": "https://safebooru.org/thumbnails/3618/thumbnail_84e0a456dbdcff9a65c202165ff891a6ebabe434.jpg", "rating": "s", "tags": " 1girl blue_horns brown_hair cowboy_shot face_in_hands floating_clothes floating_hair grey_sailor_collar grey_shirt grey_skirt highres horns long_hair long_sleeves necktie original pink_necktie pleated_skirt rasukusekai sailor_collar shirt skirt solo sparkle ", "id": "3775418", "width": "2048", "change": "1640298714", "md5": "e4e0258cf355ce5286fad4a32d231c2b", "creator_id": "168", "has_children": "false", "created_at": "Thu Dec 23 22:31:53 +0000 2021", "status": "active", "source": "https://twitter.com/hun5751/status/1356570272426463232", "has_notes": "false", "has_comments": "false", "preview_width": "150", "preview_height": "113"}, {"height": "2048", "score": "0", "file_url": "https://safebooru.org/images/3618/22075f67c02f231e4b46f3399d2c58524f90a73e.jpg", "parent_id": "", "sample_url": "https://safebooru.org/samples/3618/sample_22075f67c02f231e4b46f3399d2c58524f90a73e.jpg", "sample_width": "850", "sample_height": "850", "preview_url": "https://safebooru.org/thumbnails/3618/thumbnail_22075f67c02f231e4b46f3399d2c58524f90a73e.jpg", "rating": "s", "tags": " 1girl bangs blue_hair blush closed_eyes facing_up hands_up highres long_hair original pink_sailor_collar profile rasukusekai sailor_collar shadow shirt short_sleeves solo sparkle upper_body white_shirt ", "id": "3775417", "width": "2048", "change": "1640298713", "md5": "3c432b2facfe7eb93046a2878d1f3fa3", "creator_id": "168", "has_children": "false", "created_at": "Thu Dec 23 22:31:52 +0000 2021", "status": "active", "source": "https://twitter.com/hun5751/status/1359122369655132163", "has_notes": "false", "has_comments": "false", "preview_width": "150", "preview_height": "150"}, {"height": "1448", "score": "0", "file_url": "https://safebooru.org/images/3618/b4e3ac2fa54b950de399d2c8cc7cff9ff890cd22.jpg", "parent_id": "", "sample_url": "https://safebooru.org/samples/3618/sample_b4e3ac2fa54b950de399d2c8cc7cff9ff890cd22.jpg", "sample_width": "850", "sample_height": "601", "preview_url": "https://safebooru.org/thumbnails/3618/thumbnail_b4e3ac2fa54b950de399d2c8cc7cff9ff890cd22.jpg", "rating": "s", "tags": " 1girl blush book flower highres long_hair long_sleeves lying on_back open_book original pink_hair plant purple_sailor_collar rasukusekai reading sailor_collar shadow shirt solo white_flower white_shirt ", "id": "3775416", "width": "2048", "change": "1640298712", "md5": "63ed3b408a1891fd70c5ee28d5da3826", "creator_id": "168", "has_children": "false", "created_at": "Thu Dec 23 22:31:51 +0000 2021", "status": "active", "source": "https://twitter.com/hun5751/status/1364193455644102656", "has_notes": "false", "has_comments": "false", "preview_width": "150", "preview_height": "106"}]}}